emotlib/__init__.py
emotlib/__version__.py
emotlib/emoji_unicode_map.py
emotlib/emoticon_unicode_map.py
emotlib-1.0.1.dist-info/DESCRIPTION.rst
emotlib-1.0.1.dist-info/METADATA
emotlib-1.0.1.dist-info/RECORD
emotlib-1.0.1.dist-info/WHEEL
emotlib-1.0.1.dist-info/metadata.json
emotlib-1.0.1.dist-info/top_level.txt
