Metadata-Version: 2.0
Name: emotlib
Version: 1.0.1
Summary: Python emoji + emoticon Library
Home-page: https://github.com/steven5538/emotlib
Author: steven5538
Author-email: steven5538@gmail.com
License: MIT License
Platform: UNKNOWN
Classifier: Development Status :: 5 - Production/Stable
Classifier: Intended Audience :: Developers
Classifier: Natural Language :: Chinese (Traditional)
Classifier: License :: OSI Approved :: MIT License
Classifier: Programming Language :: Python
Classifier: Programming Language :: Python :: 2
Classifier: Programming Language :: Python :: 2.7
Classifier: Programming Language :: Python :: 3
Classifier: Programming Language :: Python :: 3.4
Classifier: Programming Language :: Python :: 3.5
Classifier: Programming Language :: Python :: 3.6
Classifier: Topic :: Communications
Classifier: Topic :: Communications :: BBS
Classifier: Topic :: Communications :: Chat
Classifier: Topic :: Communications :: Email
Classifier: Topic :: Communications :: Internet Phone
Requires-Python: >=2.6, !=3.0.*, !=3.1.*, !=3.2.*, !=3.3.*
